flatpad/__init__.py
flatpad/config.ini
flatpad/devices.json
flatpad/manage.py
flatpad/secret_key
flatpad/config/__init__.py
flatpad/config/asgi.py
flatpad/config/settings.py
flatpad/config/urls.py
flatpad/config/wsgi.py
flatpad/core/__init__.py
flatpad/core/admin.py
flatpad/core/apps.py
flatpad/core/models.py
flatpad/core/urls.py
flatpad/core/views.py
flatpad/core/migrations/0001_initial.py
flatpad/core/migrations/__init__.py
flatpad/core/static/script.js
flatpad/core/static/style.css
flatpad/core/templates/index.html
flatpad-1.0.0.data/scripts/flatpad
flatpad-1.0.0.dist-info/AUTHORS
flatpad-1.0.0.dist-info/LICENSE
flatpad-1.0.0.dist-info/METADATA
flatpad-1.0.0.dist-info/WHEEL
flatpad-1.0.0.dist-info/top_level.txt
flatpad-1.0.0.dist-info/RECORD
