Metadata-Version: 2.1
Name: flatpad
Version: 1.0.0
Summary: A simple webpage that provides a digital pad and indicates who is at home.
Home-page: https://github.com/jonathanhacker/flatpad
Author: Jonathan Hacker
Author-email: github@jhacker.de
License: UNKNOWN
Platform: UNKNOWN
Classifier: Framework :: Django
Classifier: License :: OSI Approved :: MIT License
Classifier: Programming Language :: Python :: 3
Requires-Python: >=3
Requires-Dist: bs4
Requires-Dist: django
Requires-Dist: fritzhome
Requires-Dist: lxml
Requires-Dist: netaddr
Requires-Dist: netifaces
